treelogger/__init__.py
treelogger/treelogger.py
treelogger/treeviewer.py
treelogger-0.15.dist-info/LICENSE
treelogger-0.15.dist-info/METADATA
treelogger-0.15.dist-info/WHEEL
treelogger-0.15.dist-info/top_level.txt
treelogger-0.15.dist-info/RECORD
