Metadata-Version: 2.1
Name: treelogger
Version: 0.15
Summary: Create tree structures for your logs
Home-page: UNKNOWN
Author: Hong Yang
Author-email: hong.meng.yang@outlook.com
License: MIT
Platform: UNKNOWN
Classifier: Programming Language :: Python :: 3
Classifier: License :: OSI Approved :: MIT License
Classifier: Operating System :: OS Independent
